xml2arrow/__init__.py
xml2arrow/_xml2arrow.abi3.so
xml2arrow/_xml2arrow.pyi
xml2arrow/exceptions.py
xml2arrow/py.typed
xml2arrow-0.12.0.dist-info/METADATA
xml2arrow-0.12.0.dist-info/WHEEL
xml2arrow-0.12.0.dist-info/licenses/LICENSE
xml2arrow-0.12.0.dist-info/RECORD
