Metadata-Version: 2.4
Name: xml2arrow
Version: 0.12.0
Classifier: Programming Language :: Rust
Classifier: Programming Language :: Python :: Implementation :: CPython
Classifier: License :: OSI Approved :: MIT License
Classifier: Programming Language :: Python :: 3
Classifier: Programming Language :: Python :: 3.10
Classifier: Programming Language :: Python :: 3.11
Classifier: Programming Language :: Python :: 3.12
Classifier: Programming Language :: Python :: 3.13
Classifier: Programming Language :: Python :: 3.14
Classifier: Topic :: Software Development :: Libraries
Classifier: Topic :: Software Development :: Libraries :: Python Modules
Classifier: Topic :: Text Processing :: Markup :: XML
Classifier: Intended Audience :: Developers
Classifier: Intended Audience :: Science/Research
Classifier: Operating System :: OS Independent
Requires-Dist: pyarrow>=14.0.0
Requires-Dist: pytest>=8.0.0 ; extra == 'test'
Requires-Dist: pytest-cov>=4.0.0 ; extra == 'test'
Provides-Extra: test
License-File: LICENSE
Summary: Efficiently convert XML data to Apache Arrow format.
Requires-Python: >=3.10
Project-URL: Bug Tracker, https://github.com/mluttikh/xml2arrow-python/issues
Project-URL: Homepage, https://github.com/mluttikh/xml2arrow-python
